odoo10_addon_project_model_to_task-10.0.0.1.0.99.dev19-py3.8-nspkg.pth
odoo/addons/project_model_to_task/README.rst
odoo/addons/project_model_to_task/__init__.py
odoo/addons/project_model_to_task/__manifest__.py
odoo/addons/project_model_to_task/demo/task.xml
odoo/addons/project_model_to_task/i18n/ar.po
odoo/addons/project_model_to_task/i18n/ca.po
odoo/addons/project_model_to_task/i18n/de.po
odoo/addons/project_model_to_task/i18n/el.po
odoo/addons/project_model_to_task/i18n/es.po
odoo/addons/project_model_to_task/i18n/es_CR.po
odoo/addons/project_model_to_task/i18n/es_MX.po
odoo/addons/project_model_to_task/i18n/es_VE.po
odoo/addons/project_model_to_task/i18n/fi.po
odoo/addons/project_model_to_task/i18n/fr.po
odoo/addons/project_model_to_task/i18n/gl.po
odoo/addons/project_model_to_task/i18n/hr.po
odoo/addons/project_model_to_task/i18n/hr_HR.po
odoo/addons/project_model_to_task/i18n/hu.po
odoo/addons/project_model_to_task/i18n/it.po
odoo/addons/project_model_to_task/i18n/ja.po
odoo/addons/project_model_to_task/i18n/lt.po
odoo/addons/project_model_to_task/i18n/lv.po
odoo/addons/project_model_to_task/i18n/mk.po
odoo/addons/project_model_to_task/i18n/mn.po
odoo/addons/project_model_to_task/i18n/nl.po
odoo/addons/project_model_to_task/i18n/nl_NL.po
odoo/addons/project_model_to_task/i18n/pl.po
odoo/addons/project_model_to_task/i18n/project_model_to_task.pot
odoo/addons/project_model_to_task/i18n/pt.po
odoo/addons/project_model_to_task/i18n/pt_BR.po
odoo/addons/project_model_to_task/i18n/pt_PT.po
odoo/addons/project_model_to_task/i18n/ro.po
odoo/addons/project_model_to_task/i18n/sl.po
odoo/addons/project_model_to_task/i18n/sv.po
odoo/addons/project_model_to_task/i18n/tr.po
odoo/addons/project_model_to_task/i18n/tr_TR.po
odoo/addons/project_model_to_task/i18n/uk.po
odoo/addons/project_model_to_task/i18n/zh_CN.po
odoo/addons/project_model_to_task/models/__init__.py
odoo/addons/project_model_to_task/models/action.py
odoo/addons/project_model_to_task/models/project.py
odoo10_addon_project_model_to_task-10.0.0.1.0.99.dev19.dist-info/METADATA
odoo10_addon_project_model_to_task-10.0.0.1.0.99.dev19.dist-info/WHEEL
odoo10_addon_project_model_to_task-10.0.0.1.0.99.dev19.dist-info/namespace_packages.txt
odoo10_addon_project_model_to_task-10.0.0.1.0.99.dev19.dist-info/top_level.txt
odoo10_addon_project_model_to_task-10.0.0.1.0.99.dev19.dist-info/RECORD
